sharepoint_rest_api/__init__.py
sharepoint_rest_api/admin.py
sharepoint_rest_api/apps.py
sharepoint_rest_api/client.py
sharepoint_rest_api/config.py
sharepoint_rest_api/filters.py
sharepoint_rest_api/models.py
sharepoint_rest_api/urls.py
sharepoint_rest_api/utils.py
sharepoint_rest_api/version.py
sharepoint_rest_api/builders/__init__.py
sharepoint_rest_api/builders/camlquery_builder.py
sharepoint_rest_api/builders/querystring_builder.py
sharepoint_rest_api/builders/search_request_builder.py
sharepoint_rest_api/migrations/0001_initial.py
sharepoint_rest_api/migrations/__init__.py
sharepoint_rest_api/serializers/__init__.py
sharepoint_rest_api/serializers/fields.py
sharepoint_rest_api/serializers/files.py
sharepoint_rest_api/serializers/model_serializers.py
sharepoint_rest_api/serializers/sharepoint.py
sharepoint_rest_api/views/__init__.py
sharepoint_rest_api/views/base.py
sharepoint_rest_api/views/files.py
sharepoint_rest_api/views/model_views.py
sharepoint_rest_api/views/settings_based.py
sharepoint_rest_api/views/url_based.py
sharepoint_rest_api-0.19.dist-info/METADATA
sharepoint_rest_api-0.19.dist-info/WHEEL
sharepoint_rest_api-0.19.dist-info/RECORD
