Metadata-Version: 2.4
Name: sharepoint-rest-api
Version: 0.19
Summary: Provide REST API (DRF style) for SharePoint
Author-email: Domenico Di Nicola <domdinicola@gmail.com>
License-Expression: Apache-2.0 OR MIT
Classifier: Environment :: Web Environment
Classifier: Framework :: Django
Classifier: Framework :: Django :: 3.2
Classifier: Framework :: Django :: 4.2
Classifier: Framework :: Django :: 5.2
Classifier: Intended Audience :: Developers
Classifier: Programming Language :: Python :: 3 :: Only
Classifier: Programming Language :: Python :: 3.9
Classifier: Programming Language :: Python :: 3.10
Classifier: Programming Language :: Python :: 3.11
Classifier: Programming Language :: Python :: 3.12
Classifier: Programming Language :: Python :: 3.13
Requires-Dist: django
Requires-Dist: django-filter
Requires-Dist: django-model-utils
Requires-Dist: djangorestframework
Requires-Dist: office365-rest-python-client
